<annotation>
    <folder></folder>
    <filename>1058_OL_Lunch_048_face06_x540y94w130h134.jpg</filename>
    <path>/mnt/iusers01/fatpou01/compsci01/b08593hm/scratch/Expressive/YOLOX/datasets/VOCdevkit/VOC109/data/1058_OL_Lunch_048_face06_x540y94w130h134.jpg</path>
    <source>
        <database></database>
    </source>
    <size>
        <width>130</width>
        <height>134</height>
        <depth>3</depth>
    </size>
    <segmented></segmented>
    <object>
        <name>eye</name>
        <bndbox>
            <xmin>35</xmin>
            <ymin>54</ymin>
            <xmax>55</xmax>
            <ymax>81</ymax>
        </bndbox>
    </object>
    <object>
        <name>eye</name>
        <bndbox>
            <xmin>67</xmin>
            <ymin>51</ymin>
            <xmax>93</xmax>
            <ymax>78</ymax>
        </bndbox>
    </object>
    <object>
        <name>mouth</name>
        <bndbox>
            <xmin>51</xmin>
            <ymin>86</ymin>
            <xmax>77</xmax>
            <ymax>98</ymax>
        </bndbox>
    </object>
</annotation>