<annotation>
    <folder></folder>
    <filename>1969_PlatinumJungle_051_face00_x287y894w124h122.jpg</filename>
    <path>/mnt/iusers01/fatpou01/compsci01/b08593hm/scratch/Expressive/YOLOX/datasets/VOCdevkit/VOC109/data/1969_PlatinumJungle_051_face00_x287y894w124h122.jpg</path>
    <source>
        <database></database>
    </source>
    <size>
        <width>124</width>
        <height>122</height>
        <depth>3</depth>
    </size>
    <segmented></segmented>
    <object>
        <name>eye</name>
        <bndbox>
            <xmin>33</xmin>
            <ymin>44</ymin>
            <xmax>56</xmax>
            <ymax>66</ymax>
        </bndbox>
    </object>
    <object>
        <name>eye</name>
        <bndbox>
            <xmin>67</xmin>
            <ymin>35</ymin>
            <xmax>95</xmax>
            <ymax>59</ymax>
        </bndbox>
    </object>
    <object>
        <name>mouth</name>
        <bndbox>
            <xmin>58</xmin>
            <ymin>73</ymin>
            <xmax>69</xmax>
            <ymax>83</ymax>
        </bndbox>
    </object>
</annotation>