<annotation>
    <folder></folder>
    <filename>587_RinToSiteSippuNoNaka_035_face00_x172y45w197h249.jpg</filename>
    <path>/mnt/iusers01/fatpou01/compsci01/b08593hm/scratch/Expressive/YOLOX/datasets/VOCdevkit/VOC109/data/587_RinToSiteSippuNoNaka_035_face00_x172y45w197h249.jpg</path>
    <source>
        <database></database>
    </source>
    <size>
        <width>197</width>
        <height>249</height>
        <depth>3</depth>
    </size>
    <segmented></segmented>
    <object>
        <name>eye</name>
        <bndbox>
            <xmin>76</xmin>
            <ymin>128</ymin>
            <xmax>112</xmax>
            <ymax>148</ymax>
        </bndbox>
    </object>
    <object>
        <name>eye</name>
        <bndbox>
            <xmin>149</xmin>
            <ymin>97</ymin>
            <xmax>160</xmax>
            <ymax>117</ymax>
        </bndbox>
    </object>
    <object>
        <name>mouth</name>
        <bndbox>
            <xmin>110</xmin>
            <ymin>154</ymin>
            <xmax>155</xmax>
            <ymax>212</ymax>
        </bndbox>
    </object>
</annotation>