<annotation>
    <folder></folder>
    <filename>596_RinToSiteSippuNoNaka_009_face00_x68y240w167h209.jpg</filename>
    <path>/mnt/iusers01/fatpou01/compsci01/b08593hm/scratch/Expressive/YOLOX/datasets/VOCdevkit/VOC109/data/596_RinToSiteSippuNoNaka_009_face00_x68y240w167h209.jpg</path>
    <source>
        <database></database>
    </source>
    <size>
        <width>167</width>
        <height>209</height>
        <depth>3</depth>
    </size>
    <segmented></segmented>
    <object>
        <name>eye</name>
        <bndbox>
            <xmin>63</xmin>
            <ymin>107</ymin>
            <xmax>85</xmax>
            <ymax>125</ymax>
        </bndbox>
    </object>
    <object>
        <name>eye</name>
        <bndbox>
            <xmin>116</xmin>
            <ymin>90</ymin>
            <xmax>129</xmax>
            <ymax>107</ymax>
        </bndbox>
    </object>
    <object>
        <name>mouth</name>
        <bndbox>
            <xmin>87</xmin>
            <ymin>148</ymin>
            <xmax>125</xmax>
            <ymax>164</ymax>
        </bndbox>
    </object>
</annotation>