<annotation>
    <folder></folder>
    <filename>624_NichijouSoup_009_face00_x364y616w131h143.jpg</filename>
    <path>/mnt/iusers01/fatpou01/compsci01/b08593hm/scratch/Expressive/YOLOX/datasets/VOCdevkit/VOC109/data/624_NichijouSoup_009_face00_x364y616w131h143.jpg</path>
    <source>
        <database></database>
    </source>
    <size>
        <width>131</width>
        <height>143</height>
        <depth>3</depth>
    </size>
    <segmented></segmented>
    <object>
        <name>eye</name>
        <bndbox>
            <xmin>33</xmin>
            <ymin>42</ymin>
            <xmax>62</xmax>
            <ymax>63</ymax>
        </bndbox>
    </object>
    <object>
        <name>eye</name>
        <bndbox>
            <xmin>72</xmin>
            <ymin>42</ymin>
            <xmax>101</xmax>
            <ymax>63</ymax>
        </bndbox>
    </object>
    <object>
        <name>mouth</name>
        <bndbox>
            <xmin>53</xmin>
            <ymin>90</ymin>
            <xmax>82</xmax>
            <ymax>99</ymax>
        </bndbox>
    </object>
</annotation>