<annotation>
    <folder></folder>
    <filename>69_Ningyoushi_010_face05_x586y924w149h183.jpg</filename>
    <path>/mnt/iusers01/fatpou01/compsci01/b08593hm/scratch/Expressive/YOLOX/datasets/VOCdevkit/VOC109/data/69_Ningyoushi_010_face05_x586y924w149h183.jpg</path>
    <source>
        <database></database>
    </source>
    <size>
        <width>149</width>
        <height>183</height>
        <depth>3</depth>
    </size>
    <segmented></segmented>
    <object>
        <name>eye</name>
        <bndbox>
            <xmin>46</xmin>
            <ymin>62</ymin>
            <xmax>65</xmax>
            <ymax>84</ymax>
        </bndbox>
    </object>
    <object>
        <name>eye</name>
        <bndbox>
            <xmin>86</xmin>
            <ymin>82</ymin>
            <xmax>112</xmax>
            <ymax>103</ymax>
        </bndbox>
    </object>
    <object>
        <name>mouth</name>
        <bndbox>
            <xmin>45</xmin>
            <ymin>112</ymin>
            <xmax>74</xmax>
            <ymax>139</ymax>
        </bndbox>
    </object>
</annotation>