<annotation>
    <folder></folder>
    <filename>968_MiraiSan_045_face00_x441y32w207h208.jpg</filename>
    <path>/mnt/iusers01/fatpou01/compsci01/b08593hm/scratch/Expressive/YOLOX/datasets/VOCdevkit/VOC109/data/968_MiraiSan_045_face00_x441y32w207h208.jpg</path>
    <source>
        <database></database>
    </source>
    <size>
        <width>207</width>
        <height>208</height>
        <depth>3</depth>
    </size>
    <segmented></segmented>
    <object>
        <name>eye</name>
        <bndbox>
            <xmin>37</xmin>
            <ymin>70</ymin>
            <xmax>61</xmax>
            <ymax>92</ymax>
        </bndbox>
    </object>
    <object>
        <name>eye</name>
        <bndbox>
            <xmin>90</xmin>
            <ymin>48</ymin>
            <xmax>138</xmax>
            <ymax>81</ymax>
        </bndbox>
    </object>
    <object>
        <name>mouth</name>
        <bndbox>
            <xmin>50</xmin>
            <ymin>112</ymin>
            <xmax>128</xmax>
            <ymax>142</ymax>
        </bndbox>
    </object>
</annotation>